{
  "categories": [
    { "key": "images", "en": "Images", "zh": "图片", "badge": { "en": "Images", "zh": "图片" } },
    { "key": "textCode", "en": "Text & Code", "zh": "文本 & 代码", "badge": { "en": "Text & Code", "zh": "文本 & 代码" } },
    { "key": "colors", "en": "Colors", "zh": "颜色", "badge": { "en": "Colors", "zh": "颜色" } },
    { "key": "converters", "en": "Converters", "zh": "转换器", "badge": { "en": "Converters", "zh": "转换器" } },
    { "key": "devTools", "en": "Dev Tools", "zh": "开发工具", "badge": { "en": "Dev Tools", "zh": "开发工具" } }
  ],
  "tags": [
    { "key": "open-source", "en": "Open Source", "zh": "开源" },
    { "key": "free", "en": "Free", "zh": "免费" },
    { "key": "desktop", "en": "Desktop", "zh": "桌面端" },
    { "key": "cli", "en": "CLI", "zh": "命令行" },
    { "key": "web", "en": "Web", "zh": "网页" },
    { "key": "privacy", "en": "Privacy", "zh": "隐私" }
  ],
  "featured": ["demo", "bkd"],
  "list": [
    {
      "slug": "demo",
      "category": "images",
      "logo": "logo.svg",
      "order": 1,
      "tags": ["open-source", "free", "desktop", "privacy"]
    },
    {
      "slug": "bkd",
      "category": "devTools",
      "order": 2,
      "tags": ["open-source", "free", "cli", "web"]
    }
  ]
}
